pysparkler/__init__.py
pysparkler/api.py
pysparkler/base.py
pysparkler/cli.py
pysparkler/pyspark_22_to_23.py
pysparkler/pyspark_23_to_24.py
pysparkler/pyspark_24_to_30.py
pysparkler/pyspark_31_to_32.py
pysparkler/pyspark_32_to_33.py
pysparkler/sql_21_to_33.py
pysparkler-0.8.0.dist-info/METADATA
pysparkler-0.8.0.dist-info/WHEEL
pysparkler-0.8.0.dist-info/entry_points.txt
pysparkler-0.8.0.dist-info/RECORD
