Metadata-Version: 2.1
Name: pysparkler
Version: 0.8.0
Summary: A tool that upgrades your PySpark scripts to the latest Spark version as per Spark migration Guideline
Home-page: https://github.com/holdenk/spark-upgrade
License: Apache-2.0
Author: Dhruv Pratap
Author-email: dhruv.pratap@gmail.com
Maintainer: Holden Karau
Maintainer-email: holden@pigscanfly.ca
Requires-Python: >=3.10,<4.0
Classifier: License :: OSI Approved :: Apache Software License
Classifier: Programming Language :: Python :: 3
Classifier: Programming Language :: Python :: 3.10
Classifier: Programming Language :: Python :: 3.11
Requires-Dist: click (>=8.1.3,<9.0.0)
Requires-Dist: libcst (>=1.0.1,<2.0.0)
Requires-Dist: nbformat (>=5.8.0,<6.0.0)
Requires-Dist: rich (>=13.3.3,<14.0.0)
Requires-Dist: sqlfluff (>=1.0.0,<2.0.0)
Requires-Dist: sqlfluff-plugin-sparksql-upgrade (>=0.1.0,<0.2.0)
Project-URL: Repository, https://github.com/holdenk/spark-upgrade
